[{"taxonId": 10090, "speciesNames": ["mmu", "mouse", "musmus", "musmusculus"], "genes": [{"baseSequence": "nuccore://NC_000072.6", "name": "TRBV1*00", "geneType": "V", "isFunctional": true, "chains": ["TRB"], "anchorPoints": {"UTR5Begin": 40891195, "L1Begin": 40891295, "VIntronBegin": 40891350, "L2Begin": 40891590, "FR1Begin": 40891598, "CDR1Begin": 40891676, "FR2Begin": 40891694, "CDR2Begin": 40891745, "FR3Begin": 40891763, "CDR3Begin": 40891868, "VEnd": 40891885}}, {"baseSequence": "nuccore://NC_000072.6", "name": "TRBV2*00", "geneType": "V", "isFunctional": true, "chains": ["TRB"], "anchorPoints": {"UTR5Begin": 41047455, "L1Begin": 41047555, "VIntronBegin": 41047604, "L2Begin": 41047700, "FR1Begin": 41047708, "CDR1Begin": 41047786, "FR2Begin": 41047801, "CDR2Begin": 41047852, "FR3Begin": 41047870, "CDR3Begin": 41047978, "VEnd": 41047995}}, {"baseSequence": "nuccore://NC_000072.6", "name": "TRBV3*00", "geneType": "V", "isFunctional": true, "chains": ["TRB"], "anchorPoints": {"UTR5Begin": 41048293, "L1Begin": 41048393, "VIntronBegin": 41048442, "L2Begin": 41048526, "FR1Begin": 41048534, "CDR1Begin": 41048612, "FR2Begin": 41048627, "CDR2Begin": 41048678, "FR3Begin": 41048696, "CDR3Begin": 41048807, "VEnd": 41048824}}, {"baseSequence": "nuccore://NC_000072.6", "name": "TRBV4*00", "geneType": "V", "isFunctional": true, "chains": ["TRB"], "anchorPoints": {"UTR5Begin": 41059342, "L1Begin": 41059442, "VIntronBegin": 41059491, "L2Begin": 41059591, "FR1Begin": 41059599, "CDR1Begin": 41059677, "FR2Begin": 41059692, "CDR2Begin": 41059743, "FR3Begin": 41059761, "CDR3Begin": 41059869, "VEnd": 41059886}}, {"baseSequence": "nuccore://NC_000072.6", "name": "TRBV5*00", "geneType": "V", "isFunctional": true, "chains": ["TRB"], "anchorPoints": {"UTR5Begin": 41062258, "L1Begin": 41062358, "VIntronBegin": 41062407, "L2Begin": 41062511, "FR1Begin": 41062519, "CDR1Begin": 41062594, "FR2Begin": 41062609, "CDR2Begin": 41062660, "FR3Begin": 41062678, "CDR3Begin": 41062786, "VEnd": 41062803}}, {"baseSequence": "nuccore://NC_000072.6", "name": "TRBV6*00", "geneType": "V", "isFunctional": false, "chains": ["TRB"], "anchorPoints": {"L2Begin": 41066870, "VEnd": 41067154}}, {"baseSequence": "nuccore://NC_000072.6", "name": "TRBV7*00", "geneType": "V", "isFunctional": false, "chains": ["TRB"], "anchorPoints": {"UTR5Begin": 41080152, "L1Begin": 41080252, "VIntronBegin": 41080301, "L2Begin": 41080360, "VEnd": 41080654}}, {"baseSequence": "nuccore://NC_000072.6", "name": "TRBV8*00", "geneType": "V", "isFunctional": false, "chains": ["TRB"], "anchorPoints": {"UTR5Begin": 41084568, "L1Begin": 41084668, "VIntronBegin": 41084717, "L2Begin": 41084812, "FR1Begin": 41084820, "CDR1Begin": 41084898, "FR2Begin": 41084913, "CDR2Begin": 41084964, "FR3Begin": 41084982, "CDR3Begin": 41085090, "VEnd": 41085107}}, {"baseSequence": "nuccore://NC_000072.6", "name": "TRBV9*00", "geneType": "V", "isFunctional": false, "chains": ["TRB"], "anchorPoints": {"L2Begin": 41087990, "VEnd": 41088288}}, {"baseSequence": "nuccore://NC_000072.6", "name": "TRBV10*00", "geneType": "V", "isFunctional": false, "chains": ["TRB"], "anchorPoints": {"L2Begin": 41091934, "VEnd": 41092228}}, {"baseSequence": "nuccore://NC_000072.6", "name": "TRBV11*00", "geneType": "V", "isFunctional": false, "chains": ["TRB"], "anchorPoints": {"UTR5Begin": 41106704, "L1Begin": 41106804, "VIntronBegin": 41106858, "L2Begin": 41107035, "FR1Begin": 41107035, "CDR1Begin": 41107094, "FR2Begin": 41107109, "CDR2Begin": 41107160, "FR3Begin": 41107178, "CDR3Begin": 41107286, "VEnd": 41107303}}, {"baseSequence": "nuccore://NC_000072.6", "name": "TRBV12-1*00", "geneType": "V", "isFunctional": true, "chains": ["TRB"], "anchorPoints": {"UTR5Begin": 41113466, "L1Begin": 41113566, "VIntronBegin": 41113645, "L2Begin": 41113774, "FR1Begin": 41113782, "CDR1Begin": 41113860, "FR2Begin": 41113875, "CDR2Begin": 41113926, "FR3Begin": 41113944, "CDR3Begin": 41114052, "VEnd": 41114067}}, {"baseSequence": "nuccore://NC_000072.6", "name": "TRBV12-2*00", "geneType": "V", "isFunctional": true, "chains": ["TRB"], "anchorPoints": {"UTR5Begin": 41118763, "L1Begin": 41118863, "VIntronBegin": 41118942, "L2Begin": 41119071, "FR1Begin": 41119079, "CDR1Begin": 41119157, "FR2Begin": 41119172, "CDR2Begin": 41119223, "FR3Begin": 41119241, "CDR3Begin": 41119349, "VEnd": 41119364}}, {"baseSequence": "nuccore://NC_000072.6", "name": "TRBV12-3*00", "geneType": "V", "isFunctional": false, "chains": ["TRB"], "anchorPoints": {"UTR5Begin": 41127491, "L1Begin": 41127591, "VIntronBegin": 41127670, "L2Begin": 41127783, "FR1Begin": 41127791, "CDR1Begin": 41127871, "FR2Begin": 41127886, "CDR2Begin": 41127937, "FR3Begin": 41127955, "CDR3Begin": 41128063, "VEnd": 41128076}}, {"baseSequence": "nuccore://NC_000072.6", "name": "TRBV13-1*00", "geneType": "V", "isFunctional": true, "chains": ["TRB"], "anchorPoints": {"UTR5Begin": 41115935, "L1Begin": 41116035, "VIntronBegin": 41116078, "L2Begin": 41116174, "FR1Begin": 41116182, "CDR1Begin": 41116260, "FR2Begin": 41116275, "CDR2Begin": 41116326, "FR3Begin": 41116344, "CDR3Begin": 41116452, "VEnd": 41116468}}, {"baseSequence": "nuccore://NC_000072.6", "name": "TRBV13-2*00", "geneType": "V", "isFunctional": true, "chains": ["TRB"], "anchorPoints": {"UTR5Begin": 41121295, "L1Begin": 41121395, "VIntronBegin": 41121441, "L2Begin": 41121538, "FR1Begin": 41121546, "CDR1Begin": 41121624, "FR2Begin": 41121639, "CDR2Begin": 41121690, "FR3Begin": 41121708, "CDR3Begin": 41121816, "VEnd": 41121832}}, {"baseSequence": "nuccore://NC_000072.6", "name": "TRBV13-3*00", "geneType": "V", "isFunctional": true, "chains": ["TRB"], "anchorPoints": {"UTR5Begin": 41130046, "L1Begin": 41130146, "VIntronBegin": 41130192, "L2Begin": 41130291, "FR1Begin": 41130299, "CDR1Begin": 41130377, "FR2Begin": 41130392, "CDR2Begin": 41130443, "FR3Begin": 41130461, "CDR3Begin": 41130569, "VEnd": 41130585}}, {"baseSequence": "nuccore://NC_000072.6", "name": "TRBV14*00", "geneType": "V", "isFunctional": true, "chains": ["TRB"], "anchorPoints": {"UTR5Begin": 41135066, "L1Begin": 41135166, "VIntronBegin": 41135215, "L2Begin": 41135319, "FR1Begin": 41135327, "CDR1Begin": 41135405, "FR2Begin": 41135420, "CDR2Begin": 41135471, "FR3Begin": 41135489, "CDR3Begin": 41135600, "VEnd": 41135616}}, {"baseSequence": "nuccore://NC_000072.6", "name": "TRBV15*00", "geneType": "V", "isFunctional": true, "chains": ["TRB"], "anchorPoints": {"UTR5Begin": 41141110, "L1Begin": 41141210, "VIntronBegin": 41141259, "L2Begin": 41141360, "FR1Begin": 41141368, "CDR1Begin": 41141446, "FR2Begin": 41141461, "CDR2Begin": 41141512, "FR3Begin": 41141530, "CDR3Begin": 41141641, "VEnd": 41141658}}, {"baseSequence": "nuccore://NC_000072.6", "name": "TRBV16*00", "geneType": "V", "isFunctional": true, "chains": ["TRB"], "anchorPoints": {"UTR5Begin": 41151690, "L1Begin": 41151790, "VIntronBegin": 41151839, "L2Begin": 41151932, "FR1Begin": 41151940, "CDR1Begin": 41152018, "FR2Begin": 41152033, "CDR2Begin": 41152084, "FR3Begin": 41152102, "CDR3Begin": 41152213, "VEnd": 41152230}}, {"baseSequence": "nuccore://NC_000072.6", "name": "TRBV17*00", "geneType": "V", "isFunctional": true, "chains": ["TRB"], "anchorPoints": {"UTR5Begin": 41162991, "L1Begin": 41163091, "VIntronBegin": 41163140, "L2Begin": 41163261, "FR1Begin": 41163269, "CDR1Begin": 41163347, "FR2Begin": 41163362, "CDR2Begin": 41163413, "FR3Begin": 41163431, "CDR3Begin": 41163539, "VEnd": 41163556}}, {"baseSequence": "nuccore://NC_000072.6", "name": "TRBV18*00", "geneType": "V", "isFunctional": false, "chains": ["TRB"], "anchorPoints": {"UTR5Begin": 41175036, "L1Begin": 41175136, "VIntronBegin": 41175188, "L2Begin": 41175314, "FR1Begin": 41175322, "CDR1Begin": 41175392, "FR2Begin": 41175407, "CDR2Begin": 41175467, "FR3Begin": 41175482, "CDR3Begin": 41175591, "VEnd": 41175608}}, {"baseSequence": "nuccore://NC_000072.6", "name": "TRBV19*00", "geneType": "V", "isFunctional": true, "chains": ["TRB"], "anchorPoints": {"UTR5Begin": 41178488, "L1Begin": 41178588, "VIntronBegin": 41178637, "L2Begin": 41178745, "FR1Begin": 41178762, "CDR1Begin": 41178840, "FR2Begin": 41178855, "CDR2Begin": 41178906, "FR3Begin": 41178924, "CDR3Begin": 41179032, "VEnd": 41179048}}, {"baseSequence": "nuccore://NC_000072.6", "name": "TRBV20*00", "geneType": "V", "isFunctional": true, "chains": ["TRB"], "anchorPoints": {"UTR5Begin": 41188172, "L1Begin": 41188272, "VIntronBegin": 41188303, "L2Begin": 41188673, "FR1Begin": 41188684, "CDR1Begin": 41188762, "FR2Begin": 41188780, "CDR2Begin": 41188831, "FR3Begin": 41188852, "CDR3Begin": 41188963, "VEnd": 41188977}}, {"baseSequence": "nuccore://NC_000072.6", "name": "TRBV21*00", "geneType": "V", "isFunctional": true, "chains": ["TRB"], "anchorPoints": {"UTR5Begin": 41202486, "L1Begin": 41202627, "VIntronBegin": 41202634, "L2Begin": 41202746, "FR1Begin": 41202754, "CDR1Begin": 41202832, "FR2Begin": 41202847, "CDR2Begin": 41202898, "FR3Begin": 41202916, "CDR3Begin": 41203027, "VEnd": 41203044}}, {"baseSequence": "nuccore://NC_000072.6", "name": "TRBV22*00", "geneType": "V", "isFunctional": false, "chains": ["TRB"], "anchorPoints": {"UTR5Begin": 41212022, "L1Begin": 41212122, "VIntronBegin": 41212175, "L2Begin": 41212235, "FR1Begin": 41212236, "CDR1Begin": 41212320, "FR2Begin": 41212335, "CDR2Begin": 41212389, "FR3Begin": 41212407, "CDR3Begin": 41212518, "VEnd": 41212534}}, {"baseSequence": "nuccore://NC_000072.6", "name": "TRBV23*00", "geneType": "V", "isFunctional": true, "chains": ["TRB"], "anchorPoints": {"UTR5Begin": 41215972, "L1Begin": 41216072, "VIntronBegin": 41216121, "L2Begin": 41216228, "FR1Begin": 41216236, "CDR1Begin": 41216314, "FR2Begin": 41216329, "CDR2Begin": 41216380, "FR3Begin": 41216398, "CDR3Begin": 41216509, "VEnd": 41216526}}, {"baseSequence": "nuccore://NC_000072.6", "name": "TRBV24*00", "geneType": "V", "isFunctional": true, "chains": ["TRB"], "anchorPoints": {"UTR5Begin": 41217990, "L1Begin": 41218090, "VIntronBegin": 41218139, "L2Begin": 41218259, "FR1Begin": 41218267, "CDR1Begin": 41218345, "FR2Begin": 41218360, "CDR2Begin": 41218411, "FR3Begin": 41218429, "CDR3Begin": 41218540, "VEnd": 41218557}}, {"baseSequence": "nuccore://NC_000072.6", "name": "TRBV25*00", "geneType": "V", "isFunctional": false, "chains": ["TRB"], "anchorPoints": {"UTR5Begin": 41221573, "L1Begin": 41221673, "VIntronBegin": 41221717, "L2Begin": 41221933, "FR1Begin": 41221934, "CDR1Begin": 41222008, "FR2Begin": 41222020, "CDR2Begin": 41222071, "FR3Begin": 41222092, "CDR3Begin": 41222195, "VEnd": 41222210}}, {"baseSequence": "nuccore://NC_000072.6", "name": "TRBV26*00", "geneType": "V", "isFunctional": true, "chains": ["TRB"], "anchorPoints": {"UTR5Begin": 41227424, "L1Begin": 41227524, "VIntronBegin": 41227573, "L2Begin": 41227695, "FR1Begin": 41227703, "CDR1Begin": 41227781, "FR2Begin": 41227796, "CDR2Begin": 41227847, "FR3Begin": 41227865, "CDR3Begin": 41227976, "VEnd": 41227993}}, {"baseSequence": "nuccore://NC_000072.6", "name": "TRBV27*00", "geneType": "V", "isFunctional": false, "chains": ["TRB"], "anchorPoints": {"UTR5Begin": 41258020, "L1Begin": 41258120, "VIntronBegin": 41258169, "L2Begin": 41258294, "FR1Begin": 41258302, "CDR1Begin": 41258380, "FR2Begin": 41258395, "CDR2Begin": 41258446, "FR3Begin": 41258464, "CDR3Begin": 41258565, "VEnd": 41258579}}, {"baseSequence": "nuccore://NC_000072.6", "name": "TRBV28*00", "geneType": "V", "isFunctional": false, "chains": ["TRB"], "anchorPoints": {"UTR5Begin": 41266596, "L1Begin": 41266696, "VIntronBegin": 41266745, "L2Begin": 41266878, "FR1Begin": 41266886, "CDR1Begin": 41266964, "FR2Begin": 41266979, "CDR2Begin": 41267029, "FR3Begin": 41267047, "CDR3Begin": 41267125, "VEnd": 41267150}}, {"baseSequence": "nuccore://NC_000072.6", "name": "TRBV29*00", "geneType": "V", "isFunctional": true, "chains": ["TRB"], "anchorPoints": {"UTR5Begin": 41271302, "L1Begin": 41271402, "VIntronBegin": 41271451, "L2Begin": 41271586, "FR1Begin": 41271594, "CDR1Begin": 41271672, "FR2Begin": 41271687, "CDR2Begin": 41271738, "FR3Begin": 41271756, "CDR3Begin": 41271864, "VEnd": 41271881}}, {"baseSequence": "nuccore://NC_000072.6", "name": "TRBV30*00", "geneType": "V", "isFunctional": true, "chains": ["TRB"], "anchorPoints": {"UTR5Begin": 41281275, "L1Begin": 41281375, "VIntronBegin": 41281409, "L2Begin": 41281689, "FR1Begin": 41281700, "CDR1Begin": 41281778, "FR2Begin": 41281793, "CDR2Begin": 41281844, "FR3Begin": 41281865, "CDR3Begin": 41281976, "VEnd": 41281990}}, {"baseSequence": "nuccore://NC_000072.6", "name": "TRBV31*00", "geneType": "V", "isFunctional": true, "chains": ["TRB"], "anchorPoints": {"UTR5Begin": 41558471, "L1Begin": 41558371, "VIntronBegin": 41558328, "L2Begin": 41557984, "FR1Begin": 41557976, "CDR1Begin": 41557898, "FR2Begin": 41557880, "CDR2Begin": 41557829, "FR3Begin": 41557814, "CDR3Begin": 41557706, "VEnd": 41557693}}, {"baseSequence": "nuccore://NC_000072.6", "name": "TRBD1*00", "geneType": "D", "isFunctional": true, "chains": ["TRB"], "anchorPoints": {"DBegin": 41533200, "DEnd": 41533212}}, {"baseSequence": "nuccore://NC_000072.6", "name": "TRBD2*00", "geneType": "D", "isFunctional": true, "chains": ["TRB"], "anchorPoints": {"DBegin": 41542162, "DEnd": 41542176}}, {"baseSequence": "nuccore://NC_000072.6", "name": "TRBJ1-1*00", "geneType": "J", "isFunctional": true, "chains": ["TRB"], "anchorPoints": {"JBegin": 41533863, "FR4Begin": 41533883, "FR4End": 41533911}}, {"baseSequence": "nuccore://NC_000072.6", "name": "TRBJ1-2*00", "geneType": "J", "isFunctional": true, "chains": ["TRB"], "anchorPoints": {"JBegin": 41534000, "FR4Begin": 41534020, "FR4End": 41534048}}, {"baseSequence": "nuccore://NC_000072.6", "name": "TRBJ1-3*00", "geneType": "J", "isFunctional": true, "chains": ["TRB"], "anchorPoints": {"JBegin": 41534322, "FR4Begin": 41534344, "FR4End": 41534372}}, {"baseSequence": "nuccore://NC_000072.6", "name": "TRBJ1-4*00", "geneType": "J", "isFunctional": true, "chains": ["TRB"], "anchorPoints": {"JBegin": 41534810, "FR4Begin": 41534833, "FR4End": 41534861}}, {"baseSequence": "nuccore://NC_000072.6", "name": "TRBJ1-5*00", "geneType": "J", "isFunctional": true, "chains": ["TRB"], "anchorPoints": {"JBegin": 41535083, "FR4Begin": 41535105, "FR4End": 41535133}}, {"baseSequence": "nuccore://NC_000072.6", "name": "TRBJ1-6*00", "geneType": "J", "isFunctional": true, "chains": ["TRB"], "anchorPoints": {"JBegin": 41535553, "FR4Begin": 41535578, "FR4End": 41535606}}, {"baseSequence": "nuccore://NC_000072.6", "name": "TRBJ1-7*00", "geneType": "J", "isFunctional": true, "chains": ["TRB"], "anchorPoints": {"JBegin": 41535641, "FR4Begin": 41535659, "FR4End": 41535687}}, {"baseSequence": "nuccore://NC_000072.6", "name": "TRBJ2-1*00", "geneType": "J", "isFunctional": true, "chains": ["TRB"], "anchorPoints": {"JBegin": 41542753, "FR4Begin": 41542775, "FR4End": 41542803}}, {"baseSequence": "nuccore://NC_000072.6", "name": "TRBJ2-2*00", "geneType": "J", "isFunctional": true, "chains": ["TRB"], "anchorPoints": {"JBegin": 41542956, "FR4Begin": 41542979, "FR4End": 41543007}}, {"baseSequence": "nuccore://NC_000072.6", "name": "TRBJ2-3*00", "geneType": "J", "isFunctional": true, "chains": ["TRB"], "anchorPoints": {"JBegin": 41543222, "FR4Begin": 41543243, "FR4End": 41543271}}, {"baseSequence": "nuccore://NC_000072.6", "name": "TRBJ2-4*00", "geneType": "J", "isFunctional": true, "chains": ["TRB"], "anchorPoints": {"JBegin": 41543361, "FR4Begin": 41543382, "FR4End": 41543410}}, {"baseSequence": "nuccore://NC_000072.6", "name": "TRBJ2-5*00", "geneType": "J", "isFunctional": true, "chains": ["TRB"], "anchorPoints": {"JBegin": 41543452, "FR4Begin": 41543473, "FR4End": 41543501}}, {"baseSequence": "nuccore://NC_000072.6", "name": "TRBJ2-6*00", "geneType": "J", "isFunctional": false, "chains": ["TRB"], "anchorPoints": {"JBegin": 41543597, "FR4Begin": 41543618, "FR4End": 41543645}}, {"baseSequence": "nuccore://NC_000072.6", "name": "TRBJ2-7*00", "geneType": "J", "isFunctional": true, "chains": ["TRB"], "anchorPoints": {"JBegin": 41543809, "FR4Begin": 41543828, "FR4End": 41543856}}, {"baseSequence": "nuccore://NC_000072.6", "name": "TRBC1*00", "geneType": "C", "isFunctional": true, "chains": ["TRB"], "anchorPoints": {"CBegin": 41538218, "CExon1End": 41538593, "CEnd": 41539665}}, {"baseSequence": "nuccore://NC_000072.6", "name": "TRBC2*00", "geneType": "C", "isFunctional": true, "chains": ["TRB"], "anchorPoints": {"CBegin": 41546729, "CExon1End": 41547104, "CEnd": 41548181}}]}]